.gitignore
.travis.yml
LICENSE
README.md
setup.py
jjb_pipeline/__init__.py
jjb_pipeline/definition.py
jjb_pipeline/project_pipeline.py
tests/base.py
tests/scm_pipeline.xml
tests/scm_pipeline.yml
tests/script_pipeline.xml
tests/script_pipeline.yml
tests/test_scm_pipeline.py
tests/test_script_pipeline.py
zerotk.jenkins_job_builder_pipeline.egg-info/PKG-INFO
zerotk.jenkins_job_builder_pipeline.egg-info/SOURCES.txt
zerotk.jenkins_job_builder_pipeline.egg-info/dependency_links.txt
zerotk.jenkins_job_builder_pipeline.egg-info/entry_points.txt
zerotk.jenkins_job_builder_pipeline.egg-info/requires.txt
zerotk.jenkins_job_builder_pipeline.egg-info/top_level.txt