Metadata-Version: 1.1
Name: zerotk.jenkins-job-builder-pipeline
Version: 0.1.0
Summary: Pipeline support for jenkins-job-builder
Home-page: https://github.com/rusty-dev/jenkins-job-builder-pipeline
Author: https://github.com/rusty-dev
Author-email: UNKNOWN
License: UNKNOWN
Platform: UNKNOWN
Classifier: Development Status :: 2 - Pre-Alpha
Classifier: Intended Audience :: Developers
Classifier: Natural Language :: English
Classifier: Programming Language :: Python :: 2
Classifier: Programming Language :: Python :: 2.6
Classifier: Programming Language :: Python :: 2.7
